[
  {
    "id": 19,
    "filename": "Tom-Sutton-Heating-Boiler-Care-Plans_2-1774974153958.jpg",
    "url": "/uploads/Tom-Sutton-Heating-Boiler-Care-Plans_2-1774974153958.jpg",
    "original_name": "Tom-Sutton-Heating-Boiler-Care-Plans_2.jpg",
    "mime_type": "image/jpeg",
    "file_size": 497,
    "alt_text": "",
    "uploaded_at": "2026-03-31T16:22:33.000Z"
  },
  {
    "id": 14,
    "filename": "Untitled-design-7-1774970138654.webp",
    "url": "/uploads/Untitled-design-7-1774970138654.webp",
    "original_name": "Untitled-design-7.webp",
    "mime_type": "image/webp",
    "file_size": 2,
    "alt_text": "",
    "uploaded_at": "2026-03-31T15:15:38.000Z"
  },
  {
    "id": 4,
    "filename": "favicon.png",
    "url": "https://i.postimg.cc/X7skSxGn/favicon.png",
    "original_name": "Site Favicon",
    "mime_type": "image/png",
    "file_size": 0,
    "alt_text": "",
    "uploaded_at": "2026-03-27T17:26:55.000Z"
  },
  {
    "id": 3,
    "filename": "Footer-Logos-Updated-1.webp",
    "url": "https://i.postimg.cc/nr1K1NHx/Footer-Logos-Updated-1.webp",
    "original_name": "Accreditations (Gas Safe, OFTEC, Checkatrade)",
    "mime_type": "image/webp",
    "file_size": 0,
    "alt_text": "",
    "uploaded_at": "2026-03-27T17:26:55.000Z"
  },
  {
    "id": 2,
    "filename": "SLEnergy-logo.webp",
    "url": "https://i.postimg.cc/MKPVK7HV/SLEnergy-logo.webp",
    "original_name": "SL Energy Logo (Footer)",
    "mime_type": "image/webp",
    "file_size": 0,
    "alt_text": "",
    "uploaded_at": "2026-03-27T17:26:55.000Z"
  }
]